{
  "data": {
    "attachments": {},
    "author_id": "1496841601640898563",
    "conversation_id": "1642920323443200001",
    "created_at": "2023-04-03T16:02:17.000Z",
    "edit_controls": {
      "editable_until": "2023-04-03T16:32:17.000Z",
      "edits_remaining": 5,
      "is_edit_eligible": false
    },
    "edit_history_tweet_ids": [
      "1642920465692778498"
    ],
    "entities": {
      "mentions": [
        {
          "end": 11,
          "id": "1613460289772736512",
          "start": 0,
          "username": "xiaomenglg"
        }
      ]
    },
    "geo": {},
    "id": "1642920465692778498",
    "in_reply_to_user_id": "1613460289772736512",
    "lang": "zh",
    "possibly_sensitive": false,
    "public_metrics": {
      "impression_count": 0,
      "like_count": 0,
      "quote_count": 0,
      "reply_count": 0,
      "retweet_count": 0
    },
    "referenced_tweets": [
      {
        "id": "1642920323443200001",
        "type": "replied_to"
      }
    ],
    "reply_settings": "everyone",
    "text": "@xiaomenglg 至少我看着！还是觉得开心！"
  },
  "includes": {
    "tweets": [
      {
        "attachments": {},
        "author_id": "1496841601640898563",
        "conversation_id": "1642920323443200001",
        "created_at": "2023-04-03T16:02:17.000Z",
        "edit_controls": {
          "editable_until": "2023-04-03T16:32:17.000Z",
          "edits_remaining": 5,
          "is_edit_eligible": false
        },
        "edit_history_tweet_ids": [
          "1642920465692778498"
        ],
        "entities": {
          "mentions": [
            {
              "end": 11,
              "id": "1613460289772736512",
              "start": 0,
              "username": "xiaomenglg"
            }
          ]
        },
        "geo": {},
        "id": "1642920465692778498",
        "in_reply_to_user_id": "1613460289772736512",
        "lang": "zh",
        "possibly_sensitive": false,
        "public_metrics": {
          "impression_count": 0,
          "like_count": 0,
          "quote_count": 0,
          "reply_count": 0,
          "retweet_count": 0
        },
        "referenced_tweets": [
          {
            "id": "1642920323443200001",
            "type": "replied_to"
          }
        ],
        "reply_settings": "everyone",
        "text": "@xiaomenglg 至少我看着！还是觉得开心！"
      },
      {
        "attachments": {},
        "author_id": "1613460289772736512",
        "conversation_id": "1642920323443200001",
        "created_at": "2023-04-03T16:01:43.000Z",
        "edit_controls": {
          "editable_until": "2023-04-03T16:31:43.000Z",
          "edits_remaining": 5,
          "is_edit_eligible": true
        },
        "edit_history_tweet_ids": [
          "1642920323443200001"
        ],
        "entities": {},
        "geo": {},
        "id": "1642920323443200001",
        "lang": "zh",
        "possibly_sensitive": false,
        "public_metrics": {
          "impression_count": 1,
          "like_count": 3,
          "quote_count": 0,
          "reply_count": 1,
          "retweet_count": 0
        },
        "reply_settings": "everyone",
        "text": "我活着有什么用呢？"
      }
    ],
    "users": [
      {
        "created_at": "2022-02-24T13:37:30.000Z",
        "description": "INFP-A型✟武装直升姬✟——责任监护@xiaomenglg中；鸡排宝宝！@zhajipainie8964是崽崽",
        "entities": {
          "description": {
            "mentions": [
              {
                "end": 31,
                "start": 20,
                "username": "xiaomenglg"
              },
              {
                "end": 54,
                "start": 38,
                "username": "zhajipainie8964"
              }
            ]
          }
        },
        "id": "1496841601640898563",
        "location": "Laniakea Supercluster",
        "name": "❀嶺芷鈴蘭❀",
        "pinned_tweet_id": "1642292226540617729",
        "profile_image_url": "https://pbs.twimg.com/profile_images/1639426794158784513/C-Wlv5av_normal.jpg",
        "protected": false,
        "public_metrics": {
          "followers_count": 142,
          "following_count": 258,
          "listed_count": 2,
          "tweet_count": 3933
        },
        "username": "1_048596_SG",
        "verified": false
      },
      {
        "created_at": "2023-01-12T08:58:18.000Z",
        "description": "这里是霜降，叫我小霜或霜霜都可以／古风／infp／高三牲／音游人，主修phigros，arc，lanota／会玩乙游但不多／安那其／黄推、纯政治推直接b／晚上会特意控制自己不emo，因为哭完再睡会做很可怕的梦／请不要讨厌我，我会很难过／男的不是互fo不要私信我／查成分互fo",
        "id": "1613460289772736512",
        "location": "ill city",
        "name": "霜降",
        "pinned_tweet_id": "1642563592326381568",
        "profile_image_url": "https://pbs.twimg.com/profile_images/1615738424203579394/mY5A-ZsF_normal.jpg",
        "protected": false,
        "public_metrics": {
          "followers_count": 275,
          "following_count": 104,
          "listed_count": 1,
          "tweet_count": 1674
        },
        "username": "xiaomenglg",
        "verified": false
      }
    ]
  }
}